easy_as_pypi_config/__init__.py
easy_as_pypi_config/dec_wrap.py
easy_as_pypi_config/defaults.py
easy_as_pypi_config/echo_cfg.py
easy_as_pypi_config/fileboss.py
easy_as_pypi_config/tests/file_fakes.py
easy_as_pypi_config/urable.py
easy_as_pypi_config-1.0.4.dist-info/LICENSE
easy_as_pypi_config-1.0.4.dist-info/METADATA
easy_as_pypi_config-1.0.4.dist-info/WHEEL
easy_as_pypi_config-1.0.4.dist-info/RECORD
